bithuman_runtime/__init__.py
bithuman_runtime/_version.py
bithuman_runtime/api.py
bithuman_runtime/config.py
bithuman_runtime/runtime.py
bithuman_runtime/runtime_async.py
bithuman_runtime/audio/__init__.py
bithuman_runtime/audio/audio.py
bithuman_runtime/audio/hparams.py
bithuman_runtime/audio/utils.py
bithuman_runtime/lib/__init__.py
bithuman_runtime/lib/_bithuman_runtime_py.cpython-312-x86_64-linux-gnu.so
bithuman_runtime/lib/_bithuman_runtime_py.pyi
bithuman_runtime/lib/audio_encoder.onnx
bithuman_runtime/lib/generator.py
bithuman_runtime/lib/libonnxruntime.so.1
bithuman_runtime/lib/pth2h5.py
bithuman_runtime/service/__init__.py
bithuman_runtime/service/client.py
bithuman_runtime/service/messages.py
bithuman_runtime/service/server.py
bithuman_runtime/utils/__init__.py
bithuman_runtime/utils/fps_controller.py
bithuman_runtime/utils/image.py
bithuman_runtime/utils/unzip.py
bithuman_runtime/video_graph/__init__.py
bithuman_runtime/video_graph/action_trigger.py
bithuman_runtime/video_graph/driver_video.py
bithuman_runtime/video_graph/navigator.py
bithuman_runtime/video_graph/trigger.py
bithuman_runtime/video_graph/video_script.py
bithuman_runtime-0.3.20.dist-info/METADATA
bithuman_runtime-0.3.20.dist-info/WHEEL
bithuman_runtime-0.3.20.dist-info/top_level.txt
bithuman_runtime-0.3.20.dist-info/RECORD
